tx/Config.txt
tx/LTtx_server.py
tx/__init__.py
tx/tx.py
LTtx-7.1.5.dist-info/LICENSE
LTtx-7.1.5.dist-info/METADATA
LTtx-7.1.5.dist-info/WHEEL
LTtx-7.1.5.dist-info/entry_points.txt
LTtx-7.1.5.dist-info/top_level.txt
LTtx-7.1.5.dist-info/RECORD
