Metadata-Version: 2.1
Name: LTtx
Version: 7.1.5
Summary: LTtx通信系统，更适合Python宝宝的通信组件，采用socket进行封装，另外封装了一些常用的函数，后续将不断更新
Home-page: https://github.com/95ge/LTtx
Author: 95ge
Author-email: 445646258@qq.com
License: MIT
Classifier: Programming Language :: Python :: 3
Classifier: License :: OSI Approved :: MIT License
Classifier: Operating System :: OS Independent
Requires-Python: >=3.5
License-File: LICENSE
Requires-Dist: pandas-market-calendars
Requires-Dist: pyzmq
Requires-Dist: requests
Requires-Dist: pandas
